fastharness/__init__.py
fastharness/app.py
fastharness/client.py
fastharness/core/__init__.py
fastharness/core/agent.py
fastharness/core/context.py
fastharness/core/event.py
fastharness/core/response.py
fastharness/core/skill.py
fastharness/logging.py
fastharness/py.typed
fastharness/worker/__init__.py
fastharness/worker/claude_worker.py
fastharness/worker/converter.py
fastharness-0.1.1.dist-info/WHEEL
fastharness-0.1.1.dist-info/METADATA
fastharness-0.1.1.dist-info/RECORD
