Metadata-Version: 2.3
Name: fastharness
Version: 0.1.1
Summary: Wrap Claude Agent SDK and expose agents as A2A-compliant FastAPI services
Author: Prass, The Nomadic Coder
Author-email: Prass, The Nomadic Coder <atemysemicolon@gmail.com>
Requires-Dist: claude-code-sdk>=0.0.20
Requires-Dist: fasta2a>=0.1.0
Requires-Dist: fastapi>=0.115.0
Requires-Dist: pydantic>=2.0.0
Requires-Dist: uvicorn>=0.30.0
Requires-Dist: anyio>=4.0.0
Requires-Dist: pytest>=8.0.0 ; extra == 'dev'
Requires-Dist: pytest-asyncio>=0.24.0 ; extra == 'dev'
Requires-Dist: httpx>=0.27.0 ; extra == 'dev'
Requires-Dist: mypy>=1.13.0 ; extra == 'dev'
Requires-Dist: ruff>=0.8.0 ; extra == 'dev'
Requires-Python: >=3.11
Provides-Extra: dev
